dinnovos/__init__.py
dinnovos/core.py
dinnovos/version.py
dinnovos/llms/__init__.py
dinnovos/llms/anthropic.py
dinnovos/llms/base.py
dinnovos/llms/google.py
dinnovos/llms/openai.py
dinnovos/thread/__init__.py
dinnovos/thread/thread_manager.py
dinnovos/utils/__init__.py
dinnovos/utils/chain_of_thought.py
dinnovos/utils/context_manager.py
dinnovos/utils/document_reader.py
dinnovos_agent-0.5.3.dist-info/METADATA
dinnovos_agent-0.5.3.dist-info/WHEEL
dinnovos_agent-0.5.3.dist-info/top_level.txt
dinnovos_agent-0.5.3.dist-info/RECORD
