Metadata-Version: 2.4
Name: dinnovos-agent
Version: 0.5.3
Summary: Dinnovos Agent - Agile AI Agents with multi-LLM support
Home-page: https://github.com/dinnovos/dinnovos-agent
Author: Dinnovos
Author-email: Dinnovos Agent <development.dinnovos@gmail.com>
License: MIT
Project-URL: Homepage, https://github.com/dinnovos/dinnovos-agent
Project-URL: Documentation, https://github.com/dinnovos/dinnovos-agent/docs
Project-URL: Repository, https://github.com/dinnovos/dinnovos-agent
Project-URL: Bug Tracker, https://github.com/dinnovos/dinnovos-agent/issues
Keywords: ai,agents,llm,openai,anthropic,google,gemini,dinnovos
Classifier: Development Status :: 3 - Alpha
Classifier: Intended Audience :: Developers
Classifier: License :: OSI Approved :: MIT License
Classifier: Programming Language :: Python :: 3.8
Classifier: Programming Language :: Python :: 3.9
Classifier: Programming Language :: Python :: 3.10
Classifier: Programming Language :: Python :: 3.11
Classifier: Programming Language :: Python :: 3.12
Requires-Python: >=3.8
Dynamic: author
Dynamic: home-page
Dynamic: requires-python
